{"Teams":[{"Sıra":"1","Takım":"Napoli","Puan":"71","O":"27","G":"23","B":"2","M":"2","AG":"64","YG":"16","A":"+48","Id":"91","Abbr":"NAP"},{"Sıra":"2","Takım":"Lazio","Puan":"55","O":"28","G":"16","B":"7","M":"5","AG":"44","YG":"19","A":"+25","Id":"87","Abbr":"LAZ"},{"Sıra":"3","Takım":"Inter","Puan":"50","O":"28","G":"16","B":"2","M":"10","AG":"47","YG":"32","A":"+15","Id":"85","Abbr":"INT"},{"Sıra":"4","Takım":"Roma","Puan":"50","O":"28","G":"15","B":"5","M":"8","AG":"38","YG":"26","A":"+12","Id":"92","Abbr":"ROM"},{"Sıra":"5","Takım":"Milan","Puan":"48","O":"27","G":"14","B":"6","M":"7","AG":"44","YG":"36","A":"+8","Id":"89","Abbr":"MIL"},{"Sıra":"6","Takım":"Atalanta","Puan":"48","O":"28","G":"14","B":"6","M":"8","AG":"47","YG":"32","A":"+15","Id":"79","Abbr":"ATA"},{"Sıra":"7","Takım":"Juventus","Puan":"44","O":"28","G":"18","B":"5","M":"5","AG":"46","YG":"22","A":"+24","Id":"86","Abbr":"JUV"},{"Sıra":"8","Takım":"Bologna","Puan":"40","O":"28","G":"11","B":"7","M":"10","AG":"36","YG":"36","A":"0","Id":"80","Abbr":"BOL"},{"Sıra":"9","Takım":"Fiorentina","Puan":"40","O":"28","G":"11","B":"7","M":"10","AG":"33","YG":"31","A":"+2","Id":"83","Abbr":"FIO"},{"Sıra":"10","Takım":"Udinese","Puan":"38","O":"28","G":"9","B":"11","M":"8","AG":"37","YG":"34","A":"+3","Id":"98","Abbr":"UDI"},{"Sıra":"11","Takım":"Torino","Puan":"37","O":"27","G":"10","B":"7","M":"10","AG":"29","YG":"33","A":"-4","Id":"97","Abbr":"TOR"},{"Sıra":"12","Takım":"Sassuolo","Puan":"36","O":"27","G":"10","B":"6","M":"11","AG":"35","YG":"40","A":"-5","Id":"95","Abbr":"SAS"},{"Sıra":"13","Takım":"Monza","Puan":"34","O":"28","G":"9","B":"7","M":"12","AG":"32","YG":"39","A":"-7","Id":"90","Abbr":"MON"},{"Sıra":"14","Takım":"Empoli","Puan":"28","O":"27","G":"6","B":"10","M":"11","AG":"24","YG":"36","A":"-12","Id":"82","Abbr":"EMP"},{"Sıra":"15","Takım":"Salernitana","Puan":"28","O":"28","G":"6","B":"10","M":"12","AG":"32","YG":"48","A":"-16","Id":"93","Abbr":"SAL"},{"Sıra":"16","Takım":"Lecce","Puan":"27","O":"27","G":"6","B":"9","M":"12","AG":"24","YG":"32","A":"-8","Id":"88","Abbr":"LEC"},{"Sıra":"17","Takım":"Spezia","Puan":"25","O":"28","G":"5","B":"10","M":"13","AG":"24","YG":"44","A":"-20","Id":"96","Abbr":"SPE"},{"Sıra":"18","Takım":"Hellas Verona","Puan":"19","O":"28","G":"4","B":"7","M":"17","AG":"22","YG":"42","A":"-20","Id":"84","Abbr":"HEL"},{"Sıra":"19","Takım":"Sampdoria","Puan":"15","O":"28","G":"3","B":"6","M":"19","AG":"16","YG":"47","A":"-31","Id":"94","Abbr":"SAM"},{"Sıra":"20","Takım":"Cremonese","Puan":"13","O":"28","G":"1","B":"10","M":"17","AG":"23","YG":"52","A":"-29","Id":"81","Abbr":"CRE"}]}